promptflow_vectordb/__init__.py
promptflow_vectordb/_version.py
promptflow_vectordb/connections/__init__.py
promptflow_vectordb/connections/pinecone.py
promptflow_vectordb/connections/qdrant.py
promptflow_vectordb/connections/weaviate.py
promptflow_vectordb/core/__init__.py
promptflow_vectordb/core/embeddingstore_core.py
promptflow_vectordb/core/contracts/__init__.py
promptflow_vectordb/core/contracts/config.py
promptflow_vectordb/core/contracts/constants.py
promptflow_vectordb/core/contracts/entities.py
promptflow_vectordb/core/contracts/exceptions.py
promptflow_vectordb/core/contracts/identifier_converter.py
promptflow_vectordb/core/contracts/secret.py
promptflow_vectordb/core/contracts/telemetry.py
promptflow_vectordb/core/contracts/types.py
promptflow_vectordb/core/embeddings/__init__.py
promptflow_vectordb/core/embeddings/aoai_embedding.py
promptflow_vectordb/core/embeddings/customized_embedding.py
promptflow_vectordb/core/embeddings/embedding.py
promptflow_vectordb/core/embeddings/embedding_factory.py
promptflow_vectordb/core/embeddings/empty_embedding.py
promptflow_vectordb/core/embeddings/openai_embedding.py
promptflow_vectordb/core/engine/__init__.py
promptflow_vectordb/core/engine/engine.py
promptflow_vectordb/core/engine/engine_factory.py
promptflow_vectordb/core/engine/langchain_engine.py
promptflow_vectordb/core/logging/__init__.py
promptflow_vectordb/core/logging/handlers.py
promptflow_vectordb/core/logging/loggers.py
promptflow_vectordb/core/logging/utils.py
promptflow_vectordb/core/remote_client/__init__.py
promptflow_vectordb/core/remote_client/aml_data_store_client.py
promptflow_vectordb/core/remote_client/azure_blob_client.py
promptflow_vectordb/core/remote_client/github_client.py
promptflow_vectordb/core/remote_client/http_client.py
promptflow_vectordb/core/remote_client/remote_client.py
promptflow_vectordb/core/remote_client/remote_client_factory.py
promptflow_vectordb/core/store/__init__.py
promptflow_vectordb/core/store/in_memory_store.py
promptflow_vectordb-0.2.17.dist-info/METADATA
promptflow_vectordb-0.2.17.dist-info/WHEEL
promptflow_vectordb-0.2.17.dist-info/entry_points.txt
promptflow_vectordb-0.2.17.dist-info/top_level.txt
promptflow_vectordb-0.2.17.dist-info/RECORD
