Metadata-Version: 2.4
Name: promptflow_vectordb
Version: 0.2.17
Summary: Prompt flow tools for accessing popular vector databases
Author: Microsoft Corporation
Author-email: aethercn@microsoft.com
Classifier: Programming Language :: Python :: 3
Classifier: License :: Other/Proprietary License
Requires-Dist: azure-ai-ml>=1.5.0
Requires-Dist: azure-identity>=1.12.0
Requires-Dist: azureml-rag>=0.2.37.2
Requires-Dist: langchain<0.4.0,>=0.3.0
Requires-Dist: langchain-community<0.4.0,>=0.3.0
Requires-Dist: azure-search-documents>=11.4.0
Requires-Dist: azure-cosmos>=4.7.0
Requires-Dist: pymongo
Requires-Dist: elasticsearch<9.0,>=8.12.0
Requires-Dist: faiss-cpu~=1.7.3
Requires-Dist: pinecone-client<6.0.0,>=5.0.0
Requires-Dist: langchain-pinecone<0.3.0,>=0.1.1
Requires-Dist: qdrant-client<2.0.0,>=1.8.0
Requires-Dist: langchain-qdrant
Requires-Dist: weaviate-client>=4.0.0
Requires-Dist: pymongo_schema
Requires-Dist: numpy<2.0,>=1.24.1
Requires-Dist: requests>=2.28.1
Requires-Dist: requests-cache~=1.1.1
Requires-Dist: ruamel-yaml<1.0.0,>=0.17.10
Requires-Dist: rank-bm25<0.3,>=0.2.2
Requires-Dist: psycopg2-binary<3.0.0,>=2.9.9
Requires-Dist: pgvector<0.3.0,>=0.2.5
Provides-Extra: azure
Provides-Extra: telemetry
Requires-Dist: azureml-telemetry>=1.56.0; extra == "telemetry"
Provides-Extra: hugging-face
Requires-Dist: scikit-learn; extra == "hugging-face"
Requires-Dist: sentence-transformers; extra == "hugging-face"
Requires-Dist: huggingface-hub>=0.25.1; extra == "hugging-face"
Dynamic: author
Dynamic: author-email
Dynamic: classifier
Dynamic: description
Dynamic: description-content-type
Dynamic: provides-extra
Dynamic: requires-dist
Dynamic: summary
